Workbook

Sheet Retail_Dataset
A1: Order ID | B1: Region | C1: Country | D1: Category | E1: Sales Channel | F1: Order Priority | G1: Order Date | H1: Units Sold | I1: Unit Price | J1: Unit Cost | K1: Total Revenue | L1: Profit
A2: ORD0001 | B2: East | C2: Germany | D2: Beverages | E2: Online | F2: High | G2: 44927 | H2: 235 | I2: 152.92 | J2: 153.6 | K2: =H2*I2 -> 35936.2 | L2: =K2-J2 -> 35782.6
A3: ORD0002 | B3: West | C3: India | D3: Food | E3: Online | F3: Low | G3: 44928 | H3: 341 | I3: 467.92 | J3: 139.84 | K3: =H3*I3 -> 159560.72 | L3: =K3-J3 -> 159420.88
A4: ORD0003 | B4: North | C4: India | D4: Clothing | E4: Offline | F4: High | G4: 44929 | H4: 179 | I4: 473.94 | J4: 97.14 | K4: =H4*I4 -> 84835.26 | L4: =K4-J4 -> 84738.12
A5: ORD0004 | B5: East | C5: USA | D5: Furniture | E5: Offline | F5: Medium | G5: 44930 | H5: 18 | I5: 314.53 | J5: 204.87 | K5: =H5*I5 -> 5661.54 | L5: =K5-J5 -> 5456.67
A6: ORD0005 | B6: East | C6: India | D6: Furniture | E6: Offline | F6: Medium | G6: 44931 | H6: 472 | I6: 392.79 | J6: 330.46 | K6: =H6*I6 -> 185396.88 | L6: =K6-J6 -> 185066.42
A7: ORD0006 | B7: West | C7: UK | D7: Clothing | E7: Online | F7: High | G7: 44932 | H7: 49 | I7: 308.07 | J7: 113.32 | K7: =H7*I7 -> 15095.43 | L7: =K7-J7 -> 14982.11
A8: ORD0007 | B8: North | C8: Germany | D8: Clothing | E8: Online | F8: Low | G8: 44933 | H8: 34 | I8: 244.78 | J8: 377.07 | K8: =H8*I8 -> 8322.52 | L8: =K8-J8 -> 7945.45
A9: ORD0008 | B9: North | C9: India | D9: Beverages | E9: Online | F9: High | G9: 44934 | H9: 270 | I9: 332.11 | J9: 349.59 | K9: =H9*I9 -> 89669.7 | L9: =K9-J9 -> 89320.11
A10: ORD0009 | B10: East | C10: India | D10: Beverages | E10: Online | F10: Low | G10: 44935 | H10: 404 | I10: 278.74 | J10: 66.38 | K10: =H10*I10 -> 112610.96 | L10: =K10-J10 -> 112544.58
A11: ORD0010 | B11: North | C11: USA | D11: Furniture | E11: Online | F11: Medium | G11: 44936 | H11: 452 | I11: 300.75 | J11: 314.94 | K11: =H11*I11 -> 135939 | L11: =K11-J11 -> 135624.06
A12: ORD0011 | B12: East | C12: USA | D12: Food | E12: Online | F12: Low | G12: 44937 | H12: 235 | I12: 393 | J12: 230.69 | K12: =H12*I12 -> 92355 | L12: =K12-J12 -> 92124.31
A13: ORD0012 | B13: East | C13: UK | D13: Furniture | E13: Offline | F13: Medium | G13: 44938 | H13: 481 | I13: 243.05 | J13: 227.5 | K13: =H13*I13 -> 116907.05 | L13: =K13-J13 -> 116679.55
... A25: ORD0024 | B25: West | C25: UK | D25: Electronics | E25: Offline | F25: Medium | G25: 44950 | H25: 325 | I25: 436.56 | J25: 130.37 | K25: =H25*I25 -> 141882 | L25: =K25-J25 -> 141751.63
A26: ORD0025 | B26: West | C26: India | E26: Offline | F26: Medium | G26: 44951 | H26: 185 | I26: 219.66 | J26: 11.11 | K26: =H26*I26 -> 40637.1 | L26: =K26-J26 -> 40625.99
A27: ORD0026 | B27: South | C27: India | D27: Beverages | E27: Offline | F27: High | G27: 44952 | H27: 470 | I27: 26.61 | J27: 63.21 | K27: =H27*I27 -> 12506.7 | L27: =K27-J27 -> 12443.49
A28: ORD0027 | B28: South | C28: UK | D28: Furniture | E28: Online | F28: Medium | G28: 44953 | H28: 293 | I28: 85.03 | J28: 91 | K28: =H28*I28 -> 24913.79 | L28: =K28-J28 -> 24822.79
A29: ORD0028 | B29: South | C29: UK | D29: Food | E29: Online | F29: Medium | G29: 44954 | H29: 462 | J29: 383.01 | K29: =H29*I29 -> 0 | L29: =K29-J29 -> -383.01
A30: ORD0029 | B30: West | C30: UK | D30: Beverages | E30: Offline | F30: Low | G30: 44955 | H30: 470 | I30: 328.37 | J30: 230.07 | K30: =H30*I30 -> 154333.9 | L30: =K30-J30 -> 154103.83
A31: ORD0030 | B31: West | C31: Germany | D31: Beverages | E31: Online | F31: Medium | G31: 44956 | H31: 90 | I31: 169.5 | J31: 373.23 | K31: =H31*I31 -> 15255 | L31: =K31-J31 -> 14881.77
A32: ORD0031 | B32: West | C32: India | D32: Beverages | E32: Online | F32: Low | G32: 44957 | H32: 123 | I32: 273.53 | J32: 230.92 | K32: =H32*I32 -> 33644.19 | L32: =K32-J32 -> 33413.27
A33: ORD0032 | B33: North | C33: Germany | D33: Beverages | E33: Online | F33: High | G33: 44958 | H33: 49 | I33: 249.17 | J33: 192.78 | K33: =H33*I33 -> 12209.33 | L33: =K33-J33 -> 12016.55
A34: ORD0033 | B34: West | C34: UK | D34: Beverages | E34: Online | F34: Medium | G34: 44959 | H34: 310 | I34: 45.36 | J34: 126.86 | K34: =H34*I34 -> 14061.6 | L34: =K34-J34 -> 13934.74
A35: ORD0034 | B35: South | C35: India | D35: Clothing | E35: Online | F35: Low | G35: 44960 | H35: 233 | I35: 204.61 | J35: 243.34 | K35: =H35*I35 -> 47674.13 | L35: =K35-J35 -> 47430.79
A36: ORD0035 | B36: South | C36: Germany | D36: Food | E36: Online | F36: High | G36: 44961 | H36: 327 | I36: 114.18 | J36: 57.4 | K36: =H36*I36 -> 37336.86 | L36: =K36-J36 -> 37279.46
A37: ORD0036 | B37: North | C37: Germany | D37: Beverages | E37: Online | F37: Medium | G37: 44962 | H37: 358 | I37: 212.11 | J37: 359.51 | K37: =H37*I37 -> 75935.38 | L37: =K37-J37 -> 75575.87
A38: ORD0037 | B38: West | C38: UK | D38: Food | E38: Online | F38: High | G38: 44963 | H38: 124 | J38: 332.07 | K38: =H38*I38 -> 0 | L38: =K38-J38 -> -332.07
A39: ORD0038 | B39: North | C39: India | D39: Clothing | E39: Online | F39: Medium | G39: 44964 | H39: 195 | I39: 421.02 | J39: 128.38 | K39: =H39*I39 -> 82098.9 | L39: =K39-J39 -> 81970.52
A40: ORD0039 | B40: North | C40: UK | D40: Clothing | E40: Online | F40: High | G40: 44965 | I40: 91.23 | J40: 381.21 | K40: =H40*I40 -> 0 | L40: =K40-J40 -> -381.21
A41: ORD0040 | B41: East | C41: India | D41: Food | E41: Offline | F41: High | G41: 44966 | H41: 65 | I41: 480.59 | J41: 330.43 | K41: =H41*I41 -> 31238.35 | L41: =K41-J41 -> 30907.92
A42: ORD0041 | B42: East | C42: Australia | D42: Electronics | E42: Offline | F42: Low | G42: 44967 | H42: 49 | I42: 210.87 | J42: 267.19 | K42: =H42*I42 -> 10332.63 | L42: =K42-J42 -> 10065.44
A43: ORD0042 | B43: East | C43: USA | D43: Furniture | E43: Online | F43: High | G43: 44968 | H43: 363 | I43: 423.89 | J43: 50.46 | K43: =H43*I43 -> 153872.07 | L43: =K43-J43 -> 153821.61
A44: ORD0043 | B44: South | C44: USA | D44: Electronics | E44: Offline | F44: Medium | G44: 44969 | H44: 49 | I44: 316.24 | J44: 192.34 | K44: =H44*I44 -> 15495.76 | L44: =K44-J44 -> 15303.42
A45: ORD0044 | B45: West | C45: USA | D45: Electronics | E45: Offline | F45: Medium | G45: 44970 | H45: 356 | I45: 369 | J45: 203.43 | K45: =H45*I45 -> 131364 | L45: =K45-J45 -> 131160.57
A46: ORD0045 | B46: West | C46: UK | D46: Electronics | E46: Online | F46: Low | G46: 44971 | H46: 470 | J46: 94.56 | K46: =H46*I46 -> 0 | L46: =K46-J46 -> -94.56
A47: ORD0046 | B47: West | C47: Australia | D47: Beverages | E47: Online | F47: Medium | G47: 44972 | H47: 246 | I47: 254.9 | J47: 33.83 | K47: =H47*I47 -> 62705.4 | L47: =K47-J47 -> 62671.57
A48: ORD0047 | B48: West | C48: India | D48: Clothing | E48: Online | F48: Medium | G48: 44973 | H48: 298 | I48: 273.93 | J48: 311.14 | K48: =H48*I48 -> 81631.14 | L48: =K48-J48 -> 81320
A49: ORD0048 | B49: East | C49: Germany | D49: Electronics | E49: Offline | F49: Medium | G49: 44974 | H49: 271 | I49: 259.43 | J49: 50.57 | K49: =H49*I49 -> 70305.53 | L49: =K49-J49 -> 70254.96
A50: ORD0049 | B50: South | C50: India | D50: Clothing | E50: Offline | F50: High | G50: 44975 | H50: 225 | I50: 296.09 | J50: 238.53 | K50: =H50*I50 -> 66620.25 | L50: =K50-J50 -> 66381.72
A51: ORD0050 | B51: West | C51: Germany | D51: Food | E51: Online | F51: High | G51: 44976 | H51: 156 | I51: 19.55 | J51: 374.71 | K51: =H51*I51 -> 3049.8 | L51: =K51-J51 -> 2675.09
A52: ORD0051 | B52: East | C52: India | D52: Furniture | E52: Online | F52: Medium | G52: 44977 | H52: 345 | I52: 200.78 | J52: 350.69 | K52: =H52*I52 -> 69269.1 | L52: =K52-J52 -> 68918.41
A53: ORD0052 | B53: South | C53: Australia | D53: Food | E53: Online | F53: Low | G53: 44978 | H53: 177 | I53: 305.06 | J53: 112.55 | K53: =H53*I53 -> 53995.62 | L53: =K53-J53 -> 53883.07
A54: ORD0053 | B54: East | C54: Germany | D54: Food | E54: Offline | F54: High | G54: 44979 | H54: 101 | I54: 300.87 | J54: 340.88 | K54: =H54*I54 -> 30387.87 | L54: =K54-J54 -> 30046.99
A55: ORD0054 | B55: West | C55: UK | D55: Beverages | E55: Offline | F55: Low | G55: 44980 | H55: 362 | I55: 397.51 | J55: 2.13 | K55: =H55*I55 -> 143898.62 | L55: =K55-J55 -> 143896.49
A56: ORD0055 | B56: East | C56: India | D56: Furniture | E56: Offline | F56: Medium | G56: 44981 | H56: 68 | I56: 329.23 | J56: 9.04 | K56: =H56*I56 -> 22387.64 | L56: =K56-J56 -> 22378.6
A57: ORD0056 | B57: West | C57: India | D57: Food | E57: Offline | F57: Medium | G57: 44982 | H57: 68 | I57: 496.11 | J57: 241.82 | K57: =H57*I57 -> 33735.48 | L57: =K57-J57 -> 33493.66
A58: ORD0057 | B58: West | C58: Germany | D58: Food | E58: Online | F58: High | G58: 44983 | H58: 313 | I58: 145.51 | J58: 147.19 | K58: =H58*I58 -> 45544.63 | L58: =K58-J58 -> 45397.44
... A80: ORD0079 | B80: East | C80: Australia | D80: Furniture | E80: Offline | F80: High | G80: 45005 | H80: 403 | I80: 159.51 | J80: 262.98 | K80: =H80*I80 -> 64282.53 | L80: =K80-J80 -> 64019.55
A81: ORD0080 | B81: West | C81: Australia | D81: Clothing | E81: Online | F81: High | G81: 45006 | H81: 169 | J81: 339.51 | K81: =H81*I81 -> 0 | L81: =K81-J81 -> -339.51
A82: ORD0081 | B82: East | C82: UK | D82: Beverages | E82: Online | F82: Low | G82: 45007 | H82: 372 | I82: 429.7 | J82: 290.28 | K82: =H82*I82 -> 159848.4 | L82: =K82-J82 -> 159558.12
A83: ORD0082 | B83: West | C83: Germany | D83: Electronics | E83: Offline | F83: Medium | G83: 45008 | H83: 446 | I83: 9.47 | J83: 317.25 | K83: =H83*I83 -> 4223.62 | L83: =K83-J83 -> 3906.37
A84: ORD0083 | B84: North | C84: India | D84: Furniture | E84: Online | F84: High | G84: 45009 | H84: 167 | I84: 296.26 | J84: 163.11 | K84: =H84*I84 -> 49475.42 | L84: =K84-J84 -> 49312.31
A85: ORD0084 | B85: West | C85: Australia | D85: Furniture | E85: Offline | F85: High | G85: 45010 | H85: 48 | I85: 301.36 | J85: 262.32 | K85: =H85*I85 -> 14465.28 | L85: =K85-J85 -> 14202.96
A86: ORD0085 | B86: East | C86: Australia | D86: Furniture | E86: Offline | F86: Medium | G86: 45011 | H86: 424 | I86: 201.35 | J86: 142.99 | K86: =H86*I86 -> 85372.4 | L86: =K86-J86 -> 85229.41
A87: ORD0086 | B87: East | C87: India | D87: Clothing | E87: Online | F87: High | G87: 45012 | H87: 91 | I87: 122.33 | J87: 211.15 | K87: =H87*I87 -> 11132.03 | L87: =K87-J87 -> 10920.88
A88: ORD0087 | B88: South | C88: Australia | D88: Beverages | E88: Online | F88: Medium | G88: 45013 | H88: 365 | I88: 121.16 | J88: 193.69 | K88: =H88*I88 -> 44223.4 | L88: =K88-J88 -> 44029.71
A89: ORD0088 | B89: North | C89: UK | D89: Beverages | E89: Online | F89: Medium | G89: 45014 | H89: 267 | I89: 442.44 | J89: 72.4 | K89: =H89*I89 -> 118131.48 | L89: =K89-J89 -> 118059.08
A90: ORD0089 | B90: West | C90: Germany | D90: Electronics | E90: Offline | F90: Medium | G90: 45015 | H90: 215 | I90: 223.8 | J90: 156.06 | K90: =H90*I90 -> 48117 | L90: =K90-J90 -> 47960.94
A91: ORD0090 | B91: South | C91: India | D91: Electronics | E91: Online | F91: Medium | G91: 45016 | H91: 86 | I91: 168.79 | J91: 385.6 | K91: =H91*I91 -> 14515.94 | L91: =K91-J91 -> 14130.34
A92: ORD0091 | B92: West | C92: Germany | D92: Furniture | E92: Offline | F92: Medium | G92: 45017 | H92: 486 | I92: 227.14 | J92: 100.93 | K92: =H92*I92 -> 110390.04 | L92: =K92-J92 -> 110289.11
A93: ORD0092 | B93: West | C93: Australia | D93: Electronics | E93: Offline | F93: Low | G93: 45018 | H93: 21 | J93: 55.25 | K93: =H93*I93 -> 0 | L93: =K93-J93 -> -55.25
A94: ORD0093 | B94: South | C94: Australia | D94: Clothing | E94: Offline | F94: High | G94: 45019 | H94: 304 | I94: 77.15 | J94: 168.6 | K94: =H94*I94 -> 23453.6 | L94: =K94-J94 -> 23285
A95: ORD0094 | B95: South | C95: India | D95: Beverages | E95: Online | F95: Low | G95: 45020 | H95: 459 | I95: 227.47 | J95: 316.55 | K95: =H95*I95 -> 104408.73 | L95: =K95-J95 -> 104092.18
A96: ORD0095 | B96: South | C96: UK | D96: Furniture | E96: Online | F96: High | G96: 45021 | H96: 233 | I96: 296 | J96: 233.69 | K96: =H96*I96 -> 68968 | L96: =K96-J96 -> 68734.31
A97: ORD0096 | B97: South | C97: USA | D97: Electronics | E97: Offline | F97: Low | G97: 45022 | H97: 22 | I97: 474.55 | J97: 273.03 | K97: =H97*I97 -> 10440.1 | L97: =K97-J97 -> 10167.07
A98: ORD0097 | B98: South | C98: India | D98: Clothing | E98: Online | F98: Medium | G98: 45023 | H98: 55 | I98: 130 | J98: 77.5 | K98: =H98*I98 -> 7150 | L98: =K98-J98 -> 7072.5
A99: ORD0098 | B99: West | C99: USA | D99: Clothing | E99: Online | F99: High | G99: 45024 | H99: 164 | I99: 182.83 | J99: 248.34 | K99: =H99*I99 -> 29984.12 | L99: =K99-J99 -> 29735.78
A100: ORD0099 | B100: South | C100: USA | D100: Electronics | E100: Online | F100: High | G100: 45025 | H100: 122 | I100: 192.78 | J100: 130.75 | K100: =H100*I100 -> 23519.16 | L100: =K100-J100 -> 23388.41
A101: ORD0100 | B101: North | C101: UK | D101: Beverages | E101: Offline | F101: Low | G101: 45026 | H101: 242 | I101: 304.74 | J101: 334.05 | K101: =H101*I101 -> 73747.08 | L101: =K101-J101 -> 73413.03
A102: ORD0101 | B102: East | C102: USA | D102: Electronics | E102: Offline | F102: Low | G102: 45027 | H102: 26 | I102: 181.58 | J102: 252.46 | K102: =H102*I102 -> 4721.08 | L102: =K102-J102 -> 4468.62
A103: ORD0102 | B103: South | C103: USA | D103: Furniture | E103: Online | F103: High | G103: 45028 | H103: 369 | I103: 269.09 | J103: 81.14 | K103: =H103*I103 -> 99294.21 | L103: =K103-J103 -> 99213.07
A104: ORD0103 | B104: South | C104: UK | D104: Electronics | E104: Offline | F104: Low | G104: 45029 | H104: 232 | I104: 391.99 | J104: 27.72 | K104: =H104*I104 -> 90941.68 | L104: =K104-J104 -> 90913.96
A105: ORD0104 | B105: West | C105: USA | D105: Clothing | E105: Online | F105: Low | G105: 45030 | H105: 363 | I105: 354.17 | J105: 18.97 | K105: =H105*I105 -> 128563.71 | L105: =K105-J105 -> 128544.74
... A131: ORD0130 | B131: West | C131: UK | D131: Food | E131: Offline | F131: High | G131: 45056 | H131: 251 | I131: 174.61 | J131: 330.4 | K131: =H131*I131 -> 43827.11 | L131: =K131-J131 -> 43496.71
A132: ORD0131 | B132: West | C132: India | D132: Furniture | E132: Offline | F132: High | G132: 45057 | I132: 268.46 | J132: 199.19 | K132: =H132*I132 -> 0 | L132: =K132-J132 -> -199.19
A133: ORD0132 | B133: North | C133: USA | D133: Furniture | E133: Offline | F133: High | G133: 45058 | H133: 228 | I133: 67.24 | J133: 155.77 | K133: =H133*I133 -> 15330.72 | L133: =K133-J133 -> 15174.95
A134: ORD0133 | B134: North | C134: Australia | D134: Furniture | E134: Online | F134: High | G134: 45059 | H134: 201 | I134: 70.69 | J134: 181.15 | K134: =H134*I134 -> 14208.69 | L134: =K134-J134 -> 14027.54
A135: ORD0134 | B135: North | C135: USA | D135: Clothing | E135: Online | F135: High | G135: 45060 | H135: 26 | I135: 76.05 | J135: 92.33 | K135: =H135*I135 -> 1977.3 | L135: =K135-J135 -> 1884.97
A136: ORD0135 | B136: East | C136: USA | D136: Clothing | E136: Online | F136: Low | G136: 45061 | H136: 21 | I136: 470.21 | J136: 355.98 | K136: =H136*I136 -> 9874.41 | L136: =K136-J136 -> 9518.43
A137: ORD0136 | B137: North | C137: India | D137: Furniture | E137: Offline | F137: Medium | G137: 45062 | H137: 415 | I137: 367.78 | J137: 181.35 | K137: =H137*I137 -> 152628.7 | L137: =K137-J137 -> 152447.35
A138: ORD0137 | B138: North | C138: Germany | D138: Food | E138: Offline | F138: High | G138: 45063 | H138: 410 | I138: 85.38 | J138: 353.22 | K138: =H138*I138 -> 35005.8 | L138: =K138-J138 -> 34652.58
A139: ORD0138 | B139: North | C139: USA | D139: Electronics | E139: Online | F139: Low | G139: 45064 | H139: 403 | I139: 98.23 | J139: 44.07 | K139: =H139*I139 -> 39586.69 | L139: =K139-J139 -> 39542.62
A140: ORD0139 | B140: East | C140: UK | D140: Food | E140: Offline | F140: Low | G140: 45065 | H140: 383 | I140: 366.76 | J140: 395.33 | K140: =H140*I140 -> 140469.08 | L140: =K140-J140 -> 140073.75
A141: ORD0140 | B141: North | C141: Germany | D141: Beverages | E141: Offline | F141: Low | G141: 45066 | H141: 202 | I141: 82.3 | J141: 178.42 | K141: =H141*I141 -> 16624.6 | L141: =K141-J141 -> 16446.18
A142: ORD0141 | B142: West | C142: Australia | D142: Clothing | E142: Offline | F142: Medium | G142: 45067 | H142: 31 | I142: 121.11 | J142: 21.04 | K142: =H142*I142 -> 3754.41 | L142: =K142-J142 -> 3733.37
A143: ORD0142 | B143: North | C143: India | D143: Electronics | E143: Offline | F143: High | G143: 45068 | H143: 483 | I143: 481.86 | J143: 17.13 | K143: =H143*I143 -> 232738.38 | L143: =K143-J143 -> 232721.25
A144: ORD0143 | B144: West | C144: Australia | D144: Electronics | E144: Offline | F144: Low | G144: 45069 | H144: 129 | I144: 131.38 | J144: 298.99 | K144: =H144*I144 -> 16948.02 | L144: =K144-J144 -> 16649.03
... A157: ORD0156 | B157: South | C157: USA | D157: Furniture | E157: Online | F157: Low | G157: 45082 | H157: 469 | I157: 470.73 | J157: 166.03 | K157: =H157*I157 -> 220772.37 | L157: =K157-J157 -> 220606.34
A158: ORD0157 | B158: East | C158: UK | D158: Food | E158: Online | F158: High | G158: 45083 | H158: 16 | J158: 220.75 | K158: =H158*I158 -> 0 | L158: =K158-J158 -> -220.75
A159: ORD0158 | B159: South | C159: India | D159: Electronics | E159: Offline | F159: Low | G159: 45084 | H159: 38 | I159: 335.15 | J159: 332.55 | K159: =H159*I159 -> 12735.7 | L159: =K159-J159 -> 12403.15
A160: ORD0159 | B160: North | C160: UK | E160: Offline | F160: Medium | G160: 45085 | H160: 404 | I160: 290.71 | J160: 29.35 | K160: =H160*I160 -> 117446.84 | L160: =K160-J160 -> 117417.49
A161: ORD0160 | B161: West | C161: Germany | D161: Food | E161: Online | F161: Low | G161: 45086 | H161: 42 | I161: 177.54 | J161: 170.87 | K161: =H161*I161 -> 7456.68 | L161: =K161-J161 -> 7285.81
A162: ORD0161 | B162: East | C162: USA | D162: Furniture | E162: Offline | F162: Low | G162: 45087 | H162: 143 | I162: 83.85 | J162: 34.88 | K162: =H162*I162 -> 11990.55 | L162: =K162-J162 -> 11955.67
A163: ORD0162 | B163: North | C163: USA | D163: Clothing | E163: Online | F163: High | G163: 45088 | H163: 376 | I163: 304.45 | J163: 206.83 | K163: =H163*I163 -> 114473.2 | L163: =K163-J163 -> 114266.37
A164: ORD0163 | B164: West | C164: Australia | D164: Electronics | E164: Online | F164: High | G164: 45089 | H164: 88 | I164: 162.47 | J164: 359.76 | K164: =H164*I164 -> 14297.36 | L164: =K164-J164 -> 13937.6
A165: ORD0164 | B165: West | C165: USA | D165: Beverages | E165: Online | F165: Low | G165: 45090 | H165: 425 | I165: 433.89 | J165: 313.43 | K165: =H165*I165 -> 184403.25 | L165: =K165-J165 -> 184089.82
A166: ORD0165 | B166: South | C166: Australia | D166: Beverages | E166: Offline | F166: High | G166: 45091 | H166: 444 | I166: 496.7 | J166: 92.68 | K166: =H166*I166 -> 220534.8 | L166: =K166-J166 -> 220442.12
A167: ORD0166 | B167: North | C167: India | D167: Food | E167: Online | F167: Medium | G167: 45092 | H167: 468 | I167: 377.45 | J167: 390.44 | K167: =H167*I167 -> 176646.6 | L167: =K167-J167 -> 176256.16
A168: ORD0167 | B168: West | C168: Germany | D168: Furniture | E168: Online | F168: Medium | G168: 45093 | H168: 67 | I168: 49.79 | J168: 267.61 | K168: =H168*I168 -> 3335.93 | L168: =K168-J168 -> 3068.32
A169: ORD0168 | B169: East | C169: Australia | D169: Electronics | E169: Offline | F169: High | G169: 45094 | H169: 480 | I169: 147.9 | J169: 6.15 | K169: =H169*I169 -> 70992 | L169: =K169-J169 -> 70985.85
...

Sheet QUES1
B2: Q1. Use Copilot to identify and summarize missing values in the dataset.
B4: Copilot Prompt - : | D4: Identify all columns with missing values and provide a summary of the missing data.
B6: Column Name | D6: Missing Values
B7: Region | D7: =COUNTBLANK(Retail_Dataset!B2:B351) -> 0
B8: Category | D8: =COUNTBLANK(Retail_Dataset!D2:D351) -> 10
B9: Units Sold | D9: =COUNTBLANK(Retail_Dataset!H2:H351) -> 10
B10: Unit Price | D10: =COUNTBLANK(Retail_Dataset!I2:I351) -> 10
B13: Copilot response -: | D13: Copilot analyzed the dataset and identified missing values in multiple columns. The Region and Category columns contained missing
D14: categorical values, while Units Sold and Unit Price had missing numerical entries.
D15: These missing values may affect calculations and analysis and therefore need to be addressed before further data processing.
B18: Formula Used -: =COUNTBLANK(range)

Sheet QUES2
C2: Ques 2 - | D2: Missing Value In Region .
C4: Copilot Prompt :- | E4: "Fill the missing values in the 'Region' column using the most frequent value."
C6: Solution :- | E6: The Region column contained missing values.
E7: Copilot identified the most frequently occurring region in the dataset and used it to fill the missing entries.
E8: This method ensures consistency in the dataset and avoids introducing random values.

Sheet QUES3
A2: Ques 3 :- | B2: Missing Values in Units Sold & Unit Price
A4: Copilot Prompt :- | C4: Replace missing values in 'Units Sold' and 'Unit Price' using the average (mean) of their respective columns.
A6: Solution :- | C6: The Units Sold and Unit Price columns contained missing numerical values.
C7: Copilot calculated the average value for each column and replaced the missing entries with the respective mean.
C8: This approach maintains numerical consistency and prevents bias caused by random value insertion.
A10: Suggested Values :-
A11: Units Sold | C11: Filled using column average
A12: Unit Price | C12: Filled using column average
A14: Formula Used :-=AVERAGE(range)

Sheet QUES4
A1: Ques 4 -: New Column: Total Revenue
A3: Copilot Prompt :- | C3: Add a new column named Total Revenue and calculate it using Units Sold and Unit Price.
A5: Solution :- | C5: A new column named Total Revenue was added in the Retail_Dataset sheet. Total Revenue was calculated by multiplying Units Sold with Unit Price for each order.
A7: Formula Used :- =H2*I2

Sheet QUES5
A1: Ques 5 - : | B1: Total Price for Order ID = ORD0123
A3: Copilot Prompt :- | C3: What is the total revenue for Order ID ORD0123?
A5: Solution :- | C5: The total revenue for Order ID ORD0123 was identified from the Total Revenue column in the Retail_Dataset sheet.
A7: Total Revenue :- | C7: 15849.3
A9: Formula Used :- =Units Sold * Unit Price

Sheet QUES6
A1: Region | B1: Average Profit
A2: East | B2: =AVERAGEIF(Retail_Dataset!B:B, A2, Retail_Dataset!L:L) -> 65823.338
A3: North | B3: =AVERAGEIF(Retail_Dataset!B:B, A3, Retail_Dataset!L:L) -> 65444.397
A4: South | B4: =AVERAGEIF(Retail_Dataset!B:B, A4, Retail_Dataset!L:L) -> 52497.308
A5: West | B5: =AVERAGEIF(Retail_Dataset!B:B, A5, Retail_Dataset!L:L) -> 58884.286
A7: Ques -6 :- | B7: Summary Chart of Average Profit by Region.
A9: Copilot Prompt: | C9: Create a bar chart showing the average profit for each region.
A11: Solution -: | C11: Copilot calculated the average profit for each region using
C12: the Profit column and grouped the results by Region.
C13: A bar chart was generated to visually compare the average
C14: profit across different regions,
C15: making it easier to identify high- and low-performing regions.
A17: Formula used -: =AVERAGE(range)
A21: This chart shows the average profit generated across different regions.

Sheet QUES7
A1: Ques -7 -: Create a pivot table summarizing total sales by category and region.
A3: Sum of Total Revenue | B3: Column Labels
A4: Row Labels | B4: East | C4: North | D4: South | E4: West | F4: Grand Total
A5: Beverages | B5: 888153.51 | C5: 985999.04 | D5: 1145872.8 | E5: 1833506.5 | F5: 4853531.9
A6: Clothing | B6: 1459067.6 | C6: 736434.66 | D6: 496502.89 | E6: 961692.7 | F6: 3653697.8
A7: Electronics | B7: 944943.52 | C7: 1099245.5 | D7: 892679.01 | E7: 1286638.7 | F7: 4223506.8
A8: Food | B8: 833638.81 | C8: 1498374.6 | D8: 567878.66 | E8: 792956.55 | F8: 3692848.6
A9: Furniture | B9: 1659890.5 | C9: 867213.15 | D9: 832820.25 | E9: 926634.58 | F9: 4286558.5
A10: Grand Total | B10: 5785693.9 | C10: 5187267 | D10: 3935753.7 | E10: 5801429.1 | F10: 20710144
A12: Copilot Prompt: | B12: Create a pivot table showing the sum of total revenue by category in rows and region in columns.
A14: Solution - : | B14: A pivot table was created using Category as rows and Region as columns, with Total Revenue aggregated as the sum.
B15: This table provides a clear comparison of sales performance across different categories and regions.

Sheet QUES8
A1: Ques 8 -: | B1: Build a Dashboard Combining Key KPIs and Charts.
A3: Copilot Prompt - : | C3: Use the dataset to build a dashboard that displays key KPIs including total revenue, total units sold, total profit,
C4: and average profit. Also include charts for revenue by category, profit by region, and monthly revenue trends.
A6: Solution - : | C6: Copilot created a dashboard by summarizing key performance indicators (KPIs) from the dataset.
C7: The dashboard includes total revenue, total units sold, total profit, and average profit displayed prominently at the top.
C8: Visual charts were added to represent revenue by category, average profit by region, and monthly
C9: revenue trends, providing a clear and interactive overview of business performance.
A12: KPI's Used -: | C12: Total Revenue → =SUM(Total_Revenue)
C14: Total Units Sold → =SUM(Units_Sold)
C16: Total Profit → =SUM(Profit)
C18: Average Profit → =AVERAGE(Profit)
A21: Charts Included :- | C21: Revenue by Category (Column Chart)
C23: Average Profit by Region (Bar Chart)
C25: Monthly Revenue Trend (Line Chart)
A27: Purpose of Dashboard - : | D27: This dashboard provides a consolidated view of sales and profit performance, helping stakeholders quickly analyze trends,
D28: compare regions and categories, and make data-driven decisions.

Sheet QUES9
A1: Ques - 9 | B1: Identify Top Performing Category by Total Revenue.
A3: Copilot Prompt -: | C3: Identify the product category that generates the highest total revenue using the dataset.
A5: Solution -: | C5: Copilot analyzed the dataset and calculated the total revenue for each product category by summing the Total Revenue values.
C6: After comparing all categories, Clothing emerged as the top-performing category with the highest total revenue.
C7: This indicates that the Clothing category contributes the most to overall sales performance.
A9: Metric Used :- | C9: Total Revenue = SUM(Total Revenue)
A11: Method Applied :- | C11: Group data by Category
C13: Aggregate Total Revenue for each category
C15: Compare totals to identify the highest-performing category
A17: Insight :- | C17: The Clothing category drives the maximum revenue, suggesting strong customer demand and sales performance in this segment.
